tracksim/__init__.py
tracksim/errors.py
tracksim/tracksim.py
tracksim/types.py
tracksim-0.1.1.dist-info/LICENSE
tracksim-0.1.1.dist-info/METADATA
tracksim-0.1.1.dist-info/WHEEL
tracksim-0.1.1.dist-info/RECORD
